subsetsumdfs/__init__.py
subsetsumdfs/main.py
subsetsumdfs-0.0.2.dist-info/LICENSE
subsetsumdfs-0.0.2.dist-info/METADATA
subsetsumdfs-0.0.2.dist-info/WHEEL
subsetsumdfs-0.0.2.dist-info/entry_points.txt
subsetsumdfs-0.0.2.dist-info/top_level.txt
subsetsumdfs-0.0.2.dist-info/RECORD
