Metadata-Version: 2.1
Name: subsetsumdfs
Version: 0.0.2
Summary: A PyPI package for subsetsumdfs with a Markdown README
Author: Princekumar Dobariya
Author-email: princekumardobariya@gmail.com
License-File: LICENSE
